reka/__init__.py
reka/chat/__init__.py
reka/chat/client.py
reka/client.py
reka/core/__init__.py
reka/core/api_error.py
reka/core/client_wrapper.py
reka/core/datetime_utils.py
reka/core/file.py
reka/core/http_client.py
reka/core/jsonable_encoder.py
reka/core/pydantic_utilities.py
reka/core/query_encoder.py
reka/core/remove_none_from_dict.py
reka/core/request_options.py
reka/core/unchecked_base_model.py
reka/environment.py
reka/errors/__init__.py
reka/errors/unprocessable_entity_error.py
reka/models/__init__.py
reka/models/client.py
reka/py.typed
reka/types/__init__.py
reka/types/chat_message.py
reka/types/chat_message_chunk.py
reka/types/chat_message_chunk_content_item.py
reka/types/chat_message_input_content_item.py
reka/types/chat_message_output_content_item.py
reka/types/chat_response.py
reka/types/chat_role.py
reka/types/chunk_chat_response.py
reka/types/chunk_message_response.py
reka/types/content.py
reka/types/finish_reason.py
reka/types/http_validation_error.py
reka/types/media_type.py
reka/types/message_response.py
reka/types/model.py
reka/types/tool.py
reka/types/tool_call.py
reka/types/tool_choice.py
reka/types/tool_output.py
reka/types/typed_media_content.py
reka/types/typed_text.py
reka/types/usage.py
reka/types/validation_error.py
reka/types/validation_error_loc_item.py
reka/v2/__init__.py
reka/v2/api/__init__.py
reka/v2/api/chat.py
reka/v2/api/dataset.py
reka/v2/api/driver.py
reka/v2/api/job.py
reka/v2/api/models.py
reka/v2/api/retrieval.py
reka/v2/errors.py
reka/v2/py.typed
reka/version.py
reka_api-3.2.0.dist-info/LICENSE
reka_api-3.2.0.dist-info/METADATA
reka_api-3.2.0.dist-info/WHEEL
reka_api-3.2.0.dist-info/RECORD
