Metadata-Version: 2.1
Name: reka-api
Version: 3.2.0
Summary: Reka Python SDK
License: MIT
Keywords: reka,ai,sdk
Author: Reka Team
Author-email: contact@reka.ai
Requires-Python: >=3.8,<4.0
Classifier: Intended Audience :: Developers
Classifier: License :: OSI Approved :: MIT License
Classifier: Operating System :: MacOS
Classifier: Operating System :: Microsoft :: Windows
Classifier: Operating System :: OS Independent
Classifier: Operating System :: POSIX
Classifier: Operating System :: POSIX :: Linux
Classifier: Programming Language :: Python
Classifier: Programming Language :: Python :: 3
Classifier: Programming Language :: Python :: 3.8
Classifier: Programming Language :: Python :: 3.9
Classifier: Programming Language :: Python :: 3.10
Classifier: Programming Language :: Python :: 3.11
Classifier: Programming Language :: Python :: 3.12
Classifier: Topic :: Software Development :: Libraries :: Python Modules
Classifier: Typing :: Typed
Requires-Dist: httpx (>=0.21.2)
Requires-Dist: httpx-sse (==0.4.0)
Requires-Dist: idna (>=3.7)
Requires-Dist: pydantic (>=1.9.2)
Requires-Dist: requests (>=2.31.0,<3.0.0)
Requires-Dist: typing_extensions (>=4.0.0)
Requires-Dist: urllib3 (>=2.0.7)
